netbox_lists/__init__.py
netbox_lists/py.typed
netbox_lists/api/__init__.py
netbox_lists/api/constants.py
netbox_lists/api/filtersets.py
netbox_lists/api/renderers.py
netbox_lists/api/serializers.py
netbox_lists/api/urls.py
netbox_lists/api/utils.py
netbox_lists/api/views.py
netbox_lists-4.0.3.dist-info/METADATA
netbox_lists-4.0.3.dist-info/WHEEL
netbox_lists-4.0.3.dist-info/licenses/LICENSE
netbox_lists-4.0.3.dist-info/RECORD
