Metadata-Version: 2.4
Name: netbox-lists
Version: 4.0.3
Author-email: Devon Mar <devon-mar@users.noreply.github.com>
License-Expression: Apache-2.0
License-File: LICENSE
Requires-Python: >=3.10
Requires-Dist: netaddr<2.0.0,>=0.8.0
